estapy/__init__.py
estapy/datosAgrupados.py
estapy/datosNoAgrupados.py
estapy-0.1.2.dist-info/licenses/LICENSE
estapy-0.1.2.dist-info/METADATA
estapy-0.1.2.dist-info/WHEEL
estapy-0.1.2.dist-info/top_level.txt
estapy-0.1.2.dist-info/RECORD
