Metadata-Version: 2.4
Name: estapy
Version: 0.1.2
Summary: Estadística descriptiva para datos agrupados y no agrupados
Author-email: Camilo Rodríguez <hola@camilordz.com>
License: MIT
Requires-Python: >=3.7
License-File: LICENSE
Requires-Dist: numpy
Requires-Dist: pandas
Requires-Dist: matplotlib
Requires-Dist: seaborn
Dynamic: license-file
